{
  "id": 12552,
  "events": [
    12813
  ],
  "name": "Pep Talks Podcast",
  "originalPhotoUrl": "http://bridgetown.festivalthing.com/sites/default/files/images/show-submissions/peptalks_atccover4.jpg",
  "photoUrl": "/api/img/show-images/show-peptalkspodcast-300x300.jpg",
  "sortOrder": 20,
  "bio": "A comedic look at our crumbling world with Eddie Pepitone and other funny people.",
  "copy": "A comedic look at our crumbling world with Eddie Pepitone and other funny people.",
  "pageUrl": "12552-pep-talks-podcast",
  "iTunesUrl": ""
}