{
  "id": 16581,
  "events": [],
  "emceeEvents": [],
  "name": "James Davis",
  "twitter": "",
  "website": "",
  "originalPhotoUrl": "http://bridgetown.festivalthing.com/sites/default/files/images/performers/36632_5dedfab6-22d1-42f2-9ea0-1ff1562cb983_06182015045537_large.jpg",
  "photoUrl": "/api/img/performer-images/performer-jamesdavis-300x300.jpg",
  "sortOrder": 138,
  "excludeFromList": false,
  "bio": "<p>James Davis is a rising force in comedy. Comedy Central has just given a series order to Davis' primetime TV show, <strong>The James Davis Show</strong> where Davis will explore contemporary urban topics and share his perspective on the world he grew up in through a unique, hybrid style of comedy that bridges the gap between urban and mainstream comedy. Prior to this, Davis was a recurring character on Kevin Hart’s hit show, <strong>Real Husbands of Hollywood</strong>, and a round table regular on <strong>Chelsea Lately</strong>.  James is constantly writing, directing, and producing original content for Funny Or Die and recently finished writing for James Corden’s <strong>Late Late Show</strong> on CBS. </p>\n<p>You can also catch James hosting his monthly stand-up show,<em> Urban Dictionary,</em> at the Nerdist Showroom at Meltdown Comics in Los Angeles, starring in Comedy Central’s Snapchat original series, Swag-a-Saurus, which is Comedy Centrals' most-watched Snapachat show, and performing in Comedy Central's musical number, <strong>The Jam</strong>.</p>\n",
  "pageUrl": "16581-james-davis"
}