{
  "id": 16898,
  "events": [],
  "emceeEvents": [],
  "name": "JO FIRESTONE",
  "twitter": "kingfirestorm",
  "website": "http://www.jofirestone.com/",
  "originalPhotoUrl": "http://bridgetown.festivalthing.com/sites/default/files/images/performers/jo_firestone.jpg",
  "photoUrl": "/api/img/performer-images/performer-jofirestone-300x300.jpg",
  "sortOrder": 115,
  "excludeFromList": false,
  "bio": "<p><em>Jo Firestone was selected as one 2016’s New Faces at JFL, and is becoming a staple at comedy festivals around the United States for her unique, left of center voice.  She is the co-creator and star of the popular RIOT digital series, WOMANHOOD.  She is also the creator and producer of 16 active live comedy shows in New York, including FRIENDS OF SINGLE PEOPLE, which is being developed for television.  She and her father host the long-running NY show PUNDERDOME 3000, which was recently made into a card game published by Random House.  It is currently the #1 bestselling card game <a href=\"https://www.amazon.com/Punderdome-Card-Game-Pun-Lovers/dp/1101905654\">Amazon</a>.</em></p>\n<p> </p>\n<p>“The most distinctive experimentalist in New York right now is Jo Firestone, who brings a radiant, big-hearted spirit to deeply committed stunts like hosting an Inner Beauty Pageant.”</p>\n<p>– <em>The New York Times</em></p>\n",
  "pageUrl": "16898-jo-firestone"
}