{
  "id": 6325,
  "events": [
    7622,
    7691,
    7697,
    7745
  ],
  "emceeEvents": [
    7916
  ],
  "name": "Dave Stone",
  "twitter": "",
  "sortOrder": 99999,
  "bio": "<p>Based in Los Angeles by way of Atlanta, Dave made his television debut on “The Late Late Show with Craig Ferguson” in 2013, and in the same year was selected to the prestigious “New Faces” showcase at the Just For Laughs Comedy Festival in Montreal, as well as being named one of the “12 Comics to Watch” by L.A. Weekly Magazine. </p>\n<p>Dave can also be heard voicing several characters on Adult Swim’s hit animated series “Squidbillies” on the Cartoon Network and was a co-founding member of the nationally acclaimed “Beards of Comedy Tour”, who released their sophomore album “Cardio Mix” on Comedy Central Records in 2011. Since 2008, Dave has spent 175+ days a year on the road, sharing stages with some of the industry’s brightest stars, such as Brian Regan, Patton Oswalt, Maria Bamford, Marc Maron, Kyle Kinane and John Mulaney. Dave’s laid back and self-deprecating style make him a hit with a wide variety of audiences, transcending age, race, class, gender, height and weight.</p>\n",
  "pageUrl": "6325-dave-stone"
}